{
  "aggregated_events": [
    {
      "occurrences": 4,
      "score": 8,
      "type": "pass"
    },
    {
      "occurrences": 1,
      "score": 0,
      "type": "playerOn"
    },
    {
      "occurrences": 2,
      "score": 30,
      "type": "successfulTackle"
    },
    {
      "occurrences": 2,
      "score": -4,
      "type": "unsuccessfulPass"
    },
    {
      "occurrences": 4,
      "score": -40,
      "type": "unsuccessfulTackle"
    }
  ],
  "events": [
    {
      "additional_minutes": 0,
      "corrected": false,
      "datetime": "2020-09-27T15:21:01Z",
      "id": 866214,
      "minutes": 89,
      "score": 2,
      "type": "pass"
    },
    {
      "additional_minutes": 0,
      "corrected": false,
      "datetime": "2020-09-27T15:16:31Z",
      "id": 866143,
      "minutes": 84,
      "score": -10,
      "type": "unsuccessfulTackle"
    },
    {
      "additional_minutes": 0,
      "corrected": false,
      "datetime": "2020-09-27T15:05:31Z",
      "id": 866001,
      "minutes": 73,
      "score": 2,
      "type": "pass"
    },
    {
      "additional_minutes": 0,
      "corrected": false,
      "datetime": "2020-09-27T15:13:01Z",
      "id": 866068,
      "minutes": 79,
      "score": 2,
      "type": "pass"
    },
    {
      "additional_minutes": 0,
      "corrected": false,
      "datetime": "2020-09-27T15:07:01Z",
      "id": 866040,
      "minutes": 75,
      "score": -10,
      "type": "unsuccessfulTackle"
    },
    {
      "additional_minutes": 0,
      "corrected": false,
      "datetime": "2020-09-27T15:18:31Z",
      "id": 866170,
      "minutes": 86,
      "score": 15,
      "type": "successfulTackle"
    },
    {
      "additional_minutes": 0,
      "corrected": false,
      "datetime": "2020-09-27T15:05:31Z",
      "id": 865992,
      "minutes": 72,
      "score": 0,
      "type": "playerOn"
    },
    {
      "additional_minutes": 0,
      "corrected": false,
      "datetime": "2020-09-27T15:22:01Z",
      "id": 866235,
      "minutes": 90,
      "score": -10,
      "type": "unsuccessfulTackle"
    },
    {
      "additional_minutes": 0,
      "corrected": false,
      "datetime": "2020-09-27T15:05:31Z",
      "id": 866004,
      "minutes": 73,
      "score": -2,
      "type": "unsuccessfulPass"
    },
    {
      "additional_minutes": 0,
      "corrected": false,
      "datetime": "2020-09-27T15:14:31Z",
      "id": 866128,
      "minutes": 83,
      "score": -2,
      "type": "unsuccessfulPass"
    },
    {
      "additional_minutes": 0,
      "corrected": false,
      "datetime": "2020-09-27T15:16:31Z",
      "id": 866142,
      "minutes": 84,
      "score": 15,
      "type": "successfulTackle"
    },
    {
      "additional_minutes": 0,
      "corrected": false,
      "datetime": "2020-09-27T15:16:31Z",
      "id": 866158,
      "minutes": 85,
      "score": 2,
      "type": "pass"
    },
    {
      "additional_minutes": 3,
      "corrected": false,
      "datetime": "2020-09-27T15:25:01Z",
      "id": 866258,
      "minutes": 90,
      "score": -10,
      "type": "unsuccessfulTackle"
    }
  ]
}