{
  "aggregated_events": [
    {
      "occurrences": 2,
      "score": 40,
      "type": "blockedGoalShot"
    },
    {
      "occurrences": 1,
      "score": -15,
      "type": "foul"
    },
    {
      "occurrences": 3,
      "score": 45,
      "type": "interception"
    },
    {
      "occurrences": 58,
      "score": 116,
      "type": "pass"
    },
    {
      "occurrences": 4,
      "score": 60,
      "type": "successfulTackle"
    },
    {
      "occurrences": 5,
      "score": 60,
      "type": "superPass"
    },
    {
      "occurrences": 11,
      "score": -22,
      "type": "unsuccessfulPass"
    },
    {
      "occurrences": 3,
      "score": -30,
      "type": "unsuccessfulTackle"
    }
  ],
  "events": [
    {
      "additional_minutes": 0,
      "corrected": false,
      "datetime": "2020-09-26T13:33:03Z",
      "id": 856149,
      "minutes": 1,
      "score": -2,
      "type": "unsuccessfulPass"
    },
    {
      "additional_minutes": 0,
      "corrected": false,
      "datetime": "2020-09-26T13:38:03Z",
      "id": 856570,
      "minutes": 5,
      "score": -2,
      "type": "unsuccessfulPass"
    },
    {
      "additional_minutes": 0,
      "corrected": false,
      "datetime": "2020-09-26T13:38:01Z",
      "id": 856527,
      "minutes": 3,
      "score": 2,
      "type": "pass"
    },
    {
      "additional_minutes": 0,
      "corrected": false,
      "datetime": "2020-09-26T13:38:01Z",
      "id": 856531,
      "minutes": 3,
      "score": 2,
      "type": "pass"
    },
    {
      "additional_minutes": 0,
      "corrected": false,
      "datetime": "2020-09-26T13:38:04Z",
      "id": 856599,
      "minutes": 6,
      "score": 2,
      "type": "pass"
    },
    {
      "additional_minutes": 0,
      "corrected": false,
      "datetime": "2020-09-26T13:38:02Z",
      "id": 856543,
      "minutes": 4,
      "score": 2,
      "type": "pass"
    },
    {
      "additional_minutes": 0,
      "corrected": false,
      "datetime": "2020-09-26T13:42:01Z",
      "id": 856862,
      "minutes": 9,
      "score": -2,
      "type": "unsuccessfulPass"
    },
    {
      "additional_minutes": 0,
      "corrected": false,
      "datetime": "2020-09-26T13:42:01Z",
      "id": 856861,
      "minutes": 9,
      "score": 15,
      "type": "successfulTackle"
    },
    {
      "additional_minutes": 0,
      "corrected": false,
      "datetime": "2020-09-26T13:42:02Z",
      "id": 856876,
      "minutes": 10,
      "score": 2,
      "type": "pass"
    },
    {
      "additional_minutes": 0,
      "corrected": false,
      "datetime": "2020-09-26T13:42:01Z",
      "id": 856859,
      "minutes": 9,
      "score": 15,
      "type": "successfulTackle"
    },
    {
      "additional_minutes": 0,
      "corrected": false,
      "datetime": "2020-09-26T13:52:01Z",
      "id": 857657,
      "minutes": 19,
      "score": 2,
      "type": "pass"
    },
    {
      "additional_minutes": 0,
      "corrected": false,
      "datetime": "2020-09-26T13:43:32Z",
      "id": 857083,
      "minutes": 12,
      "score": -2,
      "type": "unsuccessfulPass"
    },
    {
      "additional_minutes": 0,
      "corrected": false,
      "datetime": "2020-09-26T13:46:02Z",
      "id": 857258,
      "minutes": 14,
      "score": 2,
      "type": "pass"
    },
    {
      "additional_minutes": 0,
      "corrected": false,
      "datetime": "2020-09-26T13:46:03Z",
      "id": 857268,
      "minutes": 15,
      "score": 2,
      "type": "pass"
    },
    {
      "additional_minutes": 0,
      "corrected": false,
      "datetime": "2020-09-26T13:42:01Z",
      "id": 856848,
      "minutes": 8,
      "score": 2,
      "type": "pass"
    },
    {
      "additional_minutes": 0,
      "corrected": false,
      "datetime": "2020-09-26T13:46:01Z",
      "id": 857233,
      "minutes": 13,
      "score": 2,
      "type": "pass"
    },
    {
      "additional_minutes": 0,
      "corrected": false,
      "datetime": "2020-09-26T13:46:03Z",
      "id": 857271,
      "minutes": 15,
      "score": 2,
      "type": "pass"
    },
    {
      "additional_minutes": 0,
      "corrected": false,
      "datetime": "2020-09-26T13:46:03Z",
      "id": 857285,
      "minutes": 15,
      "score": 20,
      "type": "blockedGoalShot"
    },
    {
      "additional_minutes": 0,
      "corrected": false,
      "datetime": "2020-09-26T13:46:02Z",
      "id": 857250,
      "minutes": 14,
      "score": 2,
      "type": "pass"
    },
    {
      "additional_minutes": 0,
      "corrected": false,
      "datetime": "2020-09-26T13:52:01Z",
      "id": 857653,
      "minutes": 19,
      "score": 2,
      "type": "pass"
    },
    {
      "additional_minutes": 0,
      "corrected": false,
      "datetime": "2020-09-26T13:47:32Z",
      "id": 857413,
      "minutes": 16,
      "score": 2,
      "type": "pass"
    },
    {
      "additional_minutes": 0,
      "corrected": false,
      "datetime": "2020-09-26T13:49:02Z",
      "id": 857515,
      "minutes": 18,
      "score": 2,
      "type": "pass"
    },
    {
      "additional_minutes": 0,
      "corrected": false,
      "datetime": "2020-09-26T13:53:32Z",
      "id": 857833,
      "minutes": 21,
      "score": 2,
      "type": "pass"
    },
    {
      "additional_minutes": 0,
      "corrected": false,
      "datetime": "2020-09-26T14:00:02Z",
      "id": 858420,
      "minutes": 29,
      "score": 2,
      "type": "pass"
    },
    {
      "additional_minutes": 0,
      "corrected": false,
      "datetime": "2020-09-26T14:00:02Z",
      "id": 858424,
      "minutes": 29,
      "score": 2,
      "type": "pass"
    },
    {
      "additional_minutes": 0,
      "corrected": false,
      "datetime": "2020-09-26T13:56:32Z",
      "id": 858174,
      "minutes": 24,
      "score": 2,
      "type": "pass"
    },
    {
      "additional_minutes": 0,
      "corrected": false,
      "datetime": "2020-09-26T13:56:32Z",
      "id": 858180,
      "minutes": 25,
      "score": -10,
      "type": "unsuccessfulTackle"
    },
    {
      "additional_minutes": 0,
      "corrected": false,
      "datetime": "2020-09-26T13:57:32Z",
      "id": 858228,
      "minutes": 27,
      "score": 12,
      "type": "superPass"
    },
    {
      "additional_minutes": 0,
      "corrected": true,
      "datetime": "2020-09-26T13:53:32Z",
      "id": 857830,
      "minutes": 19,
      "score": 2,
      "type": "pass"
    },
    {
      "additional_minutes": 0,
      "corrected": false,
      "datetime": "2020-09-26T13:53:32Z",
      "id": 857836,
      "minutes": 22,
      "score": -2,
      "type": "unsuccessfulPass"
    },
    {
      "additional_minutes": 0,
      "corrected": false,
      "datetime": "2020-09-26T13:56:31Z",
      "id": 858155,
      "minutes": 23,
      "score": -2,
      "type": "unsuccessfulPass"
    },
    {
      "additional_minutes": 0,
      "corrected": false,
      "datetime": "2020-09-26T14:01:31Z",
      "id": 858511,
      "minutes": 30,
      "score": -2,
      "type": "unsuccessfulPass"
    },
    {
      "additional_minutes": 0,
      "corrected": false,
      "datetime": "2020-09-26T14:04:32Z",
      "id": 858711,
      "minutes": 33,
      "score": 2,
      "type": "pass"
    },
    {
      "additional_minutes": 0,
      "corrected": false,
      "datetime": "2020-09-26T14:06:01Z",
      "id": 858781,
      "minutes": 35,
      "score": 2,
      "type": "pass"
    },
    {
      "additional_minutes": 0,
      "corrected": false,
      "datetime": "2020-09-26T14:00:02Z",
      "id": 858418,
      "minutes": 29,
      "score": 2,
      "type": "pass"
    },
    {
      "additional_minutes": 0,
      "corrected": false,
      "datetime": "2020-09-26T14:00:03Z",
      "id": 858432,
      "minutes": 29,
      "score": 2,
      "type": "pass"
    },
    {
      "additional_minutes": 0,
      "corrected": false,
      "datetime": "2020-09-26T14:08:08Z",
      "id": 858994,
      "minutes": 36,
      "score": 2,
      "type": "pass"
    },
    {
      "additional_minutes": 0,
      "corrected": false,
      "datetime": "2020-09-26T14:06:01Z",
      "id": 858777,
      "minutes": 35,
      "score": -2,
      "type": "unsuccessfulPass"
    },
    {
      "additional_minutes": 0,
      "corrected": false,
      "datetime": "2020-09-26T14:08:07Z",
      "id": 858990,
      "minutes": 36,
      "score": 2,
      "type": "pass"
    },
    {
      "additional_minutes": 0,
      "corrected": false,
      "datetime": "2020-09-26T14:08:08Z",
      "id": 858996,
      "minutes": 36,
      "score": 2,
      "type": "pass"
    },
    {
      "additional_minutes": 0,
      "corrected": false,
      "datetime": "2020-09-26T14:06:01Z",
      "id": 858783,
      "minutes": 35,
      "score": -2,
      "type": "unsuccessfulPass"
    },
    {
      "additional_minutes": 0,
      "corrected": false,
      "datetime": "2020-09-26T14:08:07Z",
      "id": 858984,
      "minutes": 36,
      "score": 2,
      "type": "pass"
    },
    {
      "additional_minutes": 0,
      "corrected": false,
      "datetime": "2020-09-26T14:08:07Z",
      "id": 858987,
      "minutes": 36,
      "score": 2,
      "type": "pass"
    },
    {
      "additional_minutes": 0,
      "corrected": false,
      "datetime": "2020-09-26T14:08:08Z",
      "id": 859001,
      "minutes": 37,
      "score": 2,
      "type": "pass"
    },
    {
      "additional_minutes": 0,
      "corrected": false,
      "datetime": "2020-09-26T14:10:31Z",
      "id": 859191,
      "minutes": 39,
      "score": -10,
      "type": "unsuccessfulTackle"
    },
    {
      "additional_minutes": 0,
      "corrected": false,
      "datetime": "2020-09-26T14:18:02Z",
      "id": 859687,
      "minutes": 41,
      "score": 12,
      "type": "superPass"
    },
    {
      "additional_minutes": 0,
      "corrected": false,
      "datetime": "2020-09-26T14:18:02Z",
      "id": 859702,
      "minutes": 42,
      "score": 15,
      "type": "interception"
    },
    {
      "additional_minutes": 0,
      "corrected": true,
      "datetime": "2020-09-26T14:24:01Z",
      "id": 859860,
      "minutes": 1,
      "score": 2,
      "type": "pass"
    },
    {
      "additional_minutes": 0,
      "corrected": false,
      "datetime": "2020-09-26T14:18:03Z",
      "id": 859719,
      "minutes": 43,
      "score": 15,
      "type": "successfulTackle"
    },
    {
      "additional_minutes": 0,
      "corrected": false,
      "datetime": "2020-09-26T14:18:03Z",
      "id": 859723,
      "minutes": 43,
      "score": 2,
      "type": "pass"
    },
    {
      "additional_minutes": 0,
      "corrected": false,
      "datetime": "2020-09-26T14:18:04Z",
      "id": 859747,
      "minutes": 45,
      "score": 12,
      "type": "superPass"
    },
    {
      "additional_minutes": 0,
      "corrected": false,
      "datetime": "2020-09-26T14:18:01Z",
      "id": 859673,
      "minutes": 40,
      "score": 2,
      "type": "pass"
    },
    {
      "additional_minutes": 0,
      "corrected": false,
      "datetime": "2020-09-26T14:18:05Z",
      "id": 859756,
      "minutes": 45,
      "score": 2,
      "type": "pass"
    },
    {
      "additional_minutes": 0,
      "corrected": false,
      "datetime": "2020-09-26T14:18:03Z",
      "id": 859720,
      "minutes": 43,
      "score": -10,
      "type": "unsuccessfulTackle"
    },
    {
      "additional_minutes": 0,
      "corrected": false,
      "datetime": "2020-09-26T14:18:04Z",
      "id": 859740,
      "minutes": 44,
      "score": 2,
      "type": "pass"
    },
    {
      "additional_minutes": 1,
      "corrected": false,
      "datetime": "2020-09-26T14:18:05Z",
      "id": 859770,
      "minutes": 45,
      "score": 12,
      "type": "superPass"
    },
    {
      "additional_minutes": 0,
      "corrected": true,
      "datetime": "2020-09-26T13:33:03Z",
      "id": 859859,
      "minutes": 1,
      "score": 2,
      "type": "unsuccessfulPass"
    },
    {
      "additional_minutes": 0,
      "corrected": false,
      "datetime": "2020-09-26T14:37:02Z",
      "id": 860118,
      "minutes": 47,
      "score": 2,
      "type": "pass"
    },
    {
      "additional_minutes": 0,
      "corrected": false,
      "datetime": "2020-09-26T14:38:32Z",
      "id": 860288,
      "minutes": 48,
      "score": 2,
      "type": "pass"
    },
    {
      "additional_minutes": 0,
      "corrected": false,
      "datetime": "2020-09-26T14:41:02Z",
      "id": 860431,
      "minutes": 50,
      "score": 2,
      "type": "pass"
    },
    {
      "additional_minutes": 0,
      "corrected": false,
      "datetime": "2020-09-26T14:41:02Z",
      "id": 860433,
      "minutes": 50,
      "score": 2,
      "type": "pass"
    },
    {
      "additional_minutes": 0,
      "corrected": false,
      "datetime": "2020-09-26T14:38:32Z",
      "id": 860283,
      "minutes": 48,
      "score": 2,
      "type": "pass"
    },
    {
      "additional_minutes": 0,
      "corrected": false,
      "datetime": "2020-09-26T14:45:02Z",
      "id": 860770,
      "minutes": 55,
      "score": 12,
      "type": "superPass"
    },
    {
      "additional_minutes": 0,
      "corrected": false,
      "datetime": "2020-09-26T14:41:02Z",
      "id": 860435,
      "minutes": 50,
      "score": 2,
      "type": "pass"
    },
    {
      "additional_minutes": 0,
      "corrected": false,
      "datetime": "2020-09-26T14:44:33Z",
      "id": 860744,
      "minutes": 53,
      "score": 2,
      "type": "pass"
    },
    {
      "additional_minutes": 0,
      "corrected": false,
      "datetime": "2020-09-26T14:44:33Z",
      "id": 860748,
      "minutes": 54,
      "score": 2,
      "type": "pass"
    },
    {
      "additional_minutes": 0,
      "corrected": false,
      "datetime": "2020-09-26T14:45:01Z",
      "id": 860759,
      "minutes": 54,
      "score": 2,
      "type": "pass"
    },
    {
      "additional_minutes": 0,
      "corrected": false,
      "datetime": "2020-09-26T14:45:01Z",
      "id": 860756,
      "minutes": 54,
      "score": 2,
      "type": "pass"
    },
    {
      "additional_minutes": 0,
      "corrected": false,
      "datetime": "2020-09-26T14:49:32Z",
      "id": 861055,
      "minutes": 59,
      "score": 2,
      "type": "pass"
    },
    {
      "additional_minutes": 0,
      "corrected": true,
      "datetime": "2020-09-26T14:58:32Z",
      "id": 861823,
      "minutes": 68,
      "score": -15,
      "type": "interception"
    },
    {
      "additional_minutes": 0,
      "corrected": true,
      "datetime": "2020-09-26T15:00:02Z",
      "id": 861824,
      "minutes": 68,
      "score": 20,
      "type": "blockedGoalShot"
    },
    {
      "additional_minutes": 0,
      "corrected": false,
      "datetime": "2020-09-26T15:00:03Z",
      "id": 861835,
      "minutes": 69,
      "score": 15,
      "type": "interception"
    },
    {
      "additional_minutes": 0,
      "corrected": false,
      "datetime": "2020-09-26T14:58:32Z",
      "id": 861724,
      "minutes": 68,
      "score": 15,
      "type": "interception"
    },
    {
      "additional_minutes": 0,
      "corrected": false,
      "datetime": "2020-09-26T15:02:31Z",
      "id": 861954,
      "minutes": 72,
      "score": 15,
      "type": "interception"
    },
    {
      "additional_minutes": 0,
      "corrected": false,
      "datetime": "2020-09-26T14:58:32Z",
      "id": 861725,
      "minutes": 68,
      "score": -2,
      "type": "unsuccessfulPass"
    },
    {
      "additional_minutes": 0,
      "corrected": false,
      "datetime": "2020-09-26T15:11:01Z",
      "id": 862589,
      "minutes": 81,
      "score": 2,
      "type": "pass"
    },
    {
      "additional_minutes": 0,
      "corrected": false,
      "datetime": "2020-09-26T15:06:32Z",
      "id": 862285,
      "minutes": 75,
      "score": 2,
      "type": "pass"
    },
    {
      "additional_minutes": 0,
      "corrected": false,
      "datetime": "2020-09-26T15:09:03Z",
      "id": 862435,
      "minutes": 78,
      "score": -2,
      "type": "unsuccessfulPass"
    },
    {
      "additional_minutes": 0,
      "corrected": false,
      "datetime": "2020-09-26T15:09:03Z",
      "id": 862432,
      "minutes": 78,
      "score": 2,
      "type": "pass"
    },
    {
      "additional_minutes": 0,
      "corrected": false,
      "datetime": "2020-09-26T15:12:03Z",
      "id": 862665,
      "minutes": 81,
      "score": -15,
      "type": "foul"
    },
    {
      "additional_minutes": 0,
      "corrected": false,
      "datetime": "2020-09-26T15:11:01Z",
      "id": 862591,
      "minutes": 81,
      "score": 2,
      "type": "pass"
    },
    {
      "additional_minutes": 0,
      "corrected": false,
      "datetime": "2020-09-26T15:13:32Z",
      "id": 862813,
      "minutes": 83,
      "score": 2,
      "type": "pass"
    },
    {
      "additional_minutes": 0,
      "corrected": false,
      "datetime": "2020-09-26T15:16:33Z",
      "id": 862984,
      "minutes": 85,
      "score": 2,
      "type": "pass"
    },
    {
      "additional_minutes": 0,
      "corrected": false,
      "datetime": "2020-09-26T15:16:33Z",
      "id": 862982,
      "minutes": 85,
      "score": 2,
      "type": "pass"
    },
    {
      "additional_minutes": 0,
      "corrected": false,
      "datetime": "2020-09-26T15:21:34Z",
      "id": 863349,
      "minutes": 90,
      "score": 15,
      "type": "successfulTackle"
    },
    {
      "additional_minutes": 0,
      "corrected": false,
      "datetime": "2020-09-26T15:13:32Z",
      "id": 862809,
      "minutes": 83,
      "score": 2,
      "type": "pass"
    },
    {
      "additional_minutes": 0,
      "corrected": false,
      "datetime": "2020-09-26T15:17:02Z",
      "id": 863097,
      "minutes": 86,
      "score": 2,
      "type": "pass"
    },
    {
      "additional_minutes": 0,
      "corrected": false,
      "datetime": "2020-09-26T15:17:03Z",
      "id": 863105,
      "minutes": 87,
      "score": 2,
      "type": "pass"
    },
    {
      "additional_minutes": 0,
      "corrected": false,
      "datetime": "2020-09-26T15:21:33Z",
      "id": 863341,
      "minutes": 90,
      "score": 2,
      "type": "pass"
    },
    {
      "additional_minutes": 2,
      "corrected": false,
      "datetime": "2020-09-26T15:23:02Z",
      "id": 863431,
      "minutes": 90,
      "score": -2,
      "type": "unsuccessfulPass"
    },
    {
      "additional_minutes": 2,
      "corrected": false,
      "datetime": "2020-09-26T15:23:01Z",
      "id": 863412,
      "minutes": 90,
      "score": 2,
      "type": "pass"
    }
  ]
}