{
  "aggregated_events": [
    {
      "occurrences": 3,
      "score": 54,
      "type": "cross"
    },
    {
      "occurrences": 3,
      "score": -45,
      "type": "foul"
    },
    {
      "occurrences": 5,
      "score": 75,
      "type": "interception"
    },
    {
      "occurrences": 114,
      "score": 228,
      "type": "pass"
    },
    {
      "occurrences": 1,
      "score": 50,
      "type": "shotAtGoal"
    },
    {
      "occurrences": 6,
      "score": 90,
      "type": "successfulTackle"
    },
    {
      "occurrences": 4,
      "score": 48,
      "type": "superPass"
    },
    {
      "occurrences": 1,
      "score": 2,
      "type": "throwIn"
    },
    {
      "occurrences": 10,
      "score": -20,
      "type": "unsuccessfulPass"
    },
    {
      "occurrences": 6,
      "score": -60,
      "type": "unsuccessfulTackle"
    },
    {
      "occurrences": 1,
      "score": -30,
      "type": "yellowCard"
    }
  ],
  "events": [
    {
      "additional_minutes": 0,
      "corrected": false,
      "datetime": "2020-09-26T13:35:31Z",
      "id": 856350,
      "minutes": 5,
      "score": 15,
      "type": "successfulTackle"
    },
    {
      "additional_minutes": 0,
      "corrected": false,
      "datetime": "2020-09-26T13:34:30Z",
      "id": 856200,
      "minutes": 3,
      "score": 2,
      "type": "pass"
    },
    {
      "additional_minutes": 0,
      "corrected": false,
      "datetime": "2020-09-26T13:31:30Z",
      "id": 856009,
      "minutes": 1,
      "score": 2,
      "type": "pass"
    },
    {
      "additional_minutes": 0,
      "corrected": false,
      "datetime": "2020-09-26T13:33:01Z",
      "id": 856112,
      "minutes": 2,
      "score": 2,
      "type": "pass"
    },
    {
      "additional_minutes": 0,
      "corrected": false,
      "datetime": "2020-09-26T13:33:01Z",
      "id": 856116,
      "minutes": 2,
      "score": -2,
      "type": "unsuccessfulPass"
    },
    {
      "additional_minutes": 0,
      "corrected": false,
      "datetime": "2020-09-26T13:34:31Z",
      "id": 856217,
      "minutes": 4,
      "score": 12,
      "type": "superPass"
    },
    {
      "additional_minutes": 0,
      "corrected": false,
      "datetime": "2020-09-26T13:37:31Z",
      "id": 856472,
      "minutes": 6,
      "score": 50,
      "type": "shotAtGoal"
    },
    {
      "additional_minutes": 0,
      "corrected": false,
      "datetime": "2020-09-26T13:34:31Z",
      "id": 856225,
      "minutes": 4,
      "score": 2,
      "type": "pass"
    },
    {
      "additional_minutes": 0,
      "corrected": false,
      "datetime": "2020-09-26T13:35:31Z",
      "id": 856354,
      "minutes": 5,
      "score": 2,
      "type": "pass"
    },
    {
      "additional_minutes": 0,
      "corrected": false,
      "datetime": "2020-09-26T13:35:31Z",
      "id": 856356,
      "minutes": 5,
      "score": 2,
      "type": "pass"
    },
    {
      "additional_minutes": 0,
      "corrected": false,
      "datetime": "2020-09-26T13:35:31Z",
      "id": 856364,
      "minutes": 5,
      "score": 2,
      "type": "pass"
    },
    {
      "additional_minutes": 0,
      "corrected": false,
      "datetime": "2020-09-26T13:35:31Z",
      "id": 856366,
      "minutes": 5,
      "score": 2,
      "type": "pass"
    },
    {
      "additional_minutes": 0,
      "corrected": false,
      "datetime": "2020-09-26T13:35:31Z",
      "id": 856359,
      "minutes": 5,
      "score": 2,
      "type": "pass"
    },
    {
      "additional_minutes": 0,
      "corrected": false,
      "datetime": "2020-09-26T13:40:02Z",
      "id": 856753,
      "minutes": 10,
      "score": 2,
      "type": "pass"
    },
    {
      "additional_minutes": 0,
      "corrected": false,
      "datetime": "2020-09-26T13:40:02Z",
      "id": 856741,
      "minutes": 9,
      "score": 2,
      "type": "pass"
    },
    {
      "additional_minutes": 0,
      "corrected": false,
      "datetime": "2020-09-26T13:43:30Z",
      "id": 857048,
      "minutes": 12,
      "score": 2,
      "type": "pass"
    },
    {
      "additional_minutes": 0,
      "corrected": false,
      "datetime": "2020-09-26T13:53:02Z",
      "id": 857738,
      "minutes": 20,
      "score": 2,
      "type": "pass"
    },
    {
      "additional_minutes": 0,
      "corrected": false,
      "datetime": "2020-09-26T13:53:31Z",
      "id": 857820,
      "minutes": 23,
      "score": 2,
      "type": "pass"
    },
    {
      "additional_minutes": 0,
      "corrected": false,
      "datetime": "2020-09-26T13:43:31Z",
      "id": 857064,
      "minutes": 13,
      "score": 2,
      "type": "pass"
    },
    {
      "additional_minutes": 0,
      "corrected": false,
      "datetime": "2020-09-26T13:48:01Z",
      "id": 857436,
      "minutes": 17,
      "score": -2,
      "type": "unsuccessfulPass"
    },
    {
      "additional_minutes": 0,
      "corrected": false,
      "datetime": "2020-09-26T13:55:00Z",
      "id": 857888,
      "minutes": 24,
      "score": 2,
      "type": "pass"
    },
    {
      "additional_minutes": 0,
      "corrected": false,
      "datetime": "2020-09-26T13:41:31Z",
      "id": 856828,
      "minutes": 11,
      "score": 2,
      "type": "pass"
    },
    {
      "additional_minutes": 0,
      "corrected": false,
      "datetime": "2020-09-26T13:45:32Z",
      "id": 857191,
      "minutes": 15,
      "score": -2,
      "type": "unsuccessfulPass"
    },
    {
      "additional_minutes": 0,
      "corrected": false,
      "datetime": "2020-09-26T13:43:30Z",
      "id": 857043,
      "minutes": 12,
      "score": 2,
      "type": "throwIn"
    },
    {
      "additional_minutes": 0,
      "corrected": false,
      "datetime": "2020-09-26T13:47:00Z",
      "id": 857293,
      "minutes": 16,
      "score": 2,
      "type": "pass"
    },
    {
      "additional_minutes": 0,
      "corrected": false,
      "datetime": "2020-09-26T13:45:32Z",
      "id": 857184,
      "minutes": 15,
      "score": 2,
      "type": "pass"
    },
    {
      "additional_minutes": 0,
      "corrected": false,
      "datetime": "2020-09-26T13:45:32Z",
      "id": 857196,
      "minutes": 15,
      "score": 2,
      "type": "pass"
    },
    {
      "additional_minutes": 0,
      "corrected": false,
      "datetime": "2020-09-26T13:47:01Z",
      "id": 857305,
      "minutes": 17,
      "score": 2,
      "type": "pass"
    },
    {
      "additional_minutes": 0,
      "corrected": false,
      "datetime": "2020-09-26T13:49:01Z",
      "id": 857482,
      "minutes": 19,
      "score": 15,
      "type": "interception"
    },
    {
      "additional_minutes": 0,
      "corrected": false,
      "datetime": "2020-09-26T13:49:00Z",
      "id": 857480,
      "minutes": 19,
      "score": -10,
      "type": "unsuccessfulTackle"
    },
    {
      "additional_minutes": 0,
      "corrected": false,
      "datetime": "2020-09-26T13:53:01Z",
      "id": 857733,
      "minutes": 20,
      "score": 2,
      "type": "pass"
    },
    {
      "additional_minutes": 0,
      "corrected": false,
      "datetime": "2020-09-26T13:53:02Z",
      "id": 857757,
      "minutes": 21,
      "score": 2,
      "type": "pass"
    },
    {
      "additional_minutes": 0,
      "corrected": false,
      "datetime": "2020-09-26T13:53:01Z",
      "id": 857727,
      "minutes": 20,
      "score": 2,
      "type": "pass"
    },
    {
      "additional_minutes": 0,
      "corrected": false,
      "datetime": "2020-09-26T13:53:02Z",
      "id": 857742,
      "minutes": 20,
      "score": 2,
      "type": "pass"
    },
    {
      "additional_minutes": 0,
      "corrected": false,
      "datetime": "2020-09-26T13:53:03Z",
      "id": 857774,
      "minutes": 22,
      "score": 2,
      "type": "pass"
    },
    {
      "additional_minutes": 0,
      "corrected": false,
      "datetime": "2020-09-26T13:48:01Z",
      "id": 857435,
      "minutes": 17,
      "score": 15,
      "type": "interception"
    },
    {
      "additional_minutes": 0,
      "corrected": false,
      "datetime": "2020-09-26T13:48:01Z",
      "id": 857443,
      "minutes": 18,
      "score": 2,
      "type": "pass"
    },
    {
      "additional_minutes": 0,
      "corrected": false,
      "datetime": "2020-09-26T13:55:00Z",
      "id": 857890,
      "minutes": 24,
      "score": 2,
      "type": "pass"
    },
    {
      "additional_minutes": 0,
      "corrected": false,
      "datetime": "2020-09-26T13:53:03Z",
      "id": 857765,
      "minutes": 22,
      "score": 2,
      "type": "pass"
    },
    {
      "additional_minutes": 0,
      "corrected": false,
      "datetime": "2020-09-26T13:53:04Z",
      "id": 857789,
      "minutes": 23,
      "score": 2,
      "type": "pass"
    },
    {
      "additional_minutes": 0,
      "corrected": false,
      "datetime": "2020-09-26T13:55:00Z",
      "id": 857892,
      "minutes": 24,
      "score": 2,
      "type": "pass"
    },
    {
      "additional_minutes": 0,
      "corrected": false,
      "datetime": "2020-09-26T13:53:03Z",
      "id": 857782,
      "minutes": 22,
      "score": 2,
      "type": "pass"
    },
    {
      "additional_minutes": 0,
      "corrected": false,
      "datetime": "2020-09-26T13:56:01Z",
      "id": 857974,
      "minutes": 25,
      "score": -10,
      "type": "unsuccessfulTackle"
    },
    {
      "additional_minutes": 0,
      "corrected": false,
      "datetime": "2020-09-26T13:56:00Z",
      "id": 857958,
      "minutes": 25,
      "score": 2,
      "type": "pass"
    },
    {
      "additional_minutes": 0,
      "corrected": false,
      "datetime": "2020-09-26T13:57:31Z",
      "id": 858212,
      "minutes": 27,
      "score": 15,
      "type": "interception"
    },
    {
      "additional_minutes": 0,
      "corrected": false,
      "datetime": "2020-09-26T13:57:31Z",
      "id": 858218,
      "minutes": 27,
      "score": -2,
      "type": "unsuccessfulPass"
    },
    {
      "additional_minutes": 0,
      "corrected": false,
      "datetime": "2020-09-26T14:02:01Z",
      "id": 858554,
      "minutes": 32,
      "score": 2,
      "type": "pass"
    },
    {
      "additional_minutes": 0,
      "corrected": false,
      "datetime": "2020-09-26T13:59:01Z",
      "id": 858344,
      "minutes": 29,
      "score": 2,
      "type": "pass"
    },
    {
      "additional_minutes": 0,
      "corrected": false,
      "datetime": "2020-09-26T14:02:01Z",
      "id": 858552,
      "minutes": 32,
      "score": 15,
      "type": "interception"
    },
    {
      "additional_minutes": 0,
      "corrected": false,
      "datetime": "2020-09-26T13:59:01Z",
      "id": 858340,
      "minutes": 28,
      "score": -15,
      "type": "foul"
    },
    {
      "additional_minutes": 0,
      "corrected": false,
      "datetime": "2020-09-26T14:08:03Z",
      "id": 858889,
      "minutes": 34,
      "score": 2,
      "type": "pass"
    },
    {
      "additional_minutes": 0,
      "corrected": false,
      "datetime": "2020-09-26T14:08:05Z",
      "id": 858929,
      "minutes": 36,
      "score": 2,
      "type": "pass"
    },
    {
      "additional_minutes": 0,
      "corrected": false,
      "datetime": "2020-09-26T14:08:05Z",
      "id": 858933,
      "minutes": 36,
      "score": 15,
      "type": "successfulTackle"
    },
    {
      "additional_minutes": 0,
      "corrected": false,
      "datetime": "2020-09-26T14:08:01Z",
      "id": 858853,
      "minutes": 32,
      "score": 2,
      "type": "pass"
    },
    {
      "additional_minutes": 0,
      "corrected": false,
      "datetime": "2020-09-26T14:08:01Z",
      "id": 858855,
      "minutes": 32,
      "score": 2,
      "type": "pass"
    },
    {
      "additional_minutes": 0,
      "corrected": false,
      "datetime": "2020-09-26T14:08:02Z",
      "id": 858882,
      "minutes": 34,
      "score": 2,
      "type": "pass"
    },
    {
      "additional_minutes": 0,
      "corrected": false,
      "datetime": "2020-09-26T14:08:04Z",
      "id": 858916,
      "minutes": 35,
      "score": 2,
      "type": "pass"
    },
    {
      "additional_minutes": 0,
      "corrected": false,
      "datetime": "2020-09-26T14:08:01Z",
      "id": 858859,
      "minutes": 32,
      "score": 2,
      "type": "pass"
    },
    {
      "additional_minutes": 0,
      "corrected": false,
      "datetime": "2020-09-26T14:08:04Z",
      "id": 858914,
      "minutes": 35,
      "score": 2,
      "type": "pass"
    },
    {
      "additional_minutes": 0,
      "corrected": false,
      "datetime": "2020-09-26T14:08:05Z",
      "id": 858925,
      "minutes": 36,
      "score": 2,
      "type": "pass"
    },
    {
      "additional_minutes": 0,
      "corrected": false,
      "datetime": "2020-09-26T14:08:06Z",
      "id": 858950,
      "minutes": 37,
      "score": 2,
      "type": "pass"
    },
    {
      "additional_minutes": 0,
      "corrected": false,
      "datetime": "2020-09-26T14:08:05Z",
      "id": 858934,
      "minutes": 36,
      "score": 2,
      "type": "pass"
    },
    {
      "additional_minutes": 0,
      "corrected": false,
      "datetime": "2020-09-26T14:15:01Z",
      "id": 859525,
      "minutes": 45,
      "score": 12,
      "type": "superPass"
    },
    {
      "additional_minutes": 0,
      "corrected": false,
      "datetime": "2020-09-26T14:08:06Z",
      "id": 858955,
      "minutes": 37,
      "score": 2,
      "type": "pass"
    },
    {
      "additional_minutes": 0,
      "corrected": false,
      "datetime": "2020-09-26T14:12:33Z",
      "id": 859317,
      "minutes": 41,
      "score": 2,
      "type": "pass"
    },
    {
      "additional_minutes": 0,
      "corrected": false,
      "datetime": "2020-09-26T14:12:33Z",
      "id": 859321,
      "minutes": 41,
      "score": 2,
      "type": "pass"
    },
    {
      "additional_minutes": 0,
      "corrected": false,
      "datetime": "2020-09-26T14:08:02Z",
      "id": 858879,
      "minutes": 33,
      "score": 2,
      "type": "pass"
    },
    {
      "additional_minutes": 0,
      "corrected": false,
      "datetime": "2020-09-26T14:08:03Z",
      "id": 858884,
      "minutes": 34,
      "score": 2,
      "type": "pass"
    },
    {
      "additional_minutes": 0,
      "corrected": false,
      "datetime": "2020-09-26T14:08:05Z",
      "id": 858927,
      "minutes": 36,
      "score": 2,
      "type": "pass"
    },
    {
      "additional_minutes": 0,
      "corrected": false,
      "datetime": "2020-09-26T14:12:33Z",
      "id": 859331,
      "minutes": 41,
      "score": -2,
      "type": "unsuccessfulPass"
    },
    {
      "additional_minutes": 0,
      "corrected": false,
      "datetime": "2020-09-26T14:08:06Z",
      "id": 858953,
      "minutes": 37,
      "score": 2,
      "type": "pass"
    },
    {
      "additional_minutes": 0,
      "corrected": false,
      "datetime": "2020-09-26T14:09:01Z",
      "id": 859053,
      "minutes": 39,
      "score": -15,
      "type": "foul"
    },
    {
      "additional_minutes": 0,
      "corrected": false,
      "datetime": "2020-09-26T14:12:33Z",
      "id": 859330,
      "minutes": 41,
      "score": 15,
      "type": "successfulTackle"
    },
    {
      "additional_minutes": 1,
      "corrected": false,
      "datetime": "2020-09-26T14:16:31Z",
      "id": 859611,
      "minutes": 45,
      "score": 15,
      "type": "successfulTackle"
    },
    {
      "additional_minutes": 0,
      "corrected": false,
      "datetime": "2020-09-26T14:12:33Z",
      "id": 859319,
      "minutes": 41,
      "score": 2,
      "type": "pass"
    },
    {
      "additional_minutes": 0,
      "corrected": false,
      "datetime": "2020-09-26T14:15:02Z",
      "id": 859528,
      "minutes": 45,
      "score": 2,
      "type": "pass"
    },
    {
      "additional_minutes": 1,
      "corrected": false,
      "datetime": "2020-09-26T14:16:31Z",
      "id": 859612,
      "minutes": 45,
      "score": 2,
      "type": "pass"
    },
    {
      "additional_minutes": 1,
      "corrected": false,
      "datetime": "2020-09-26T14:16:31Z",
      "id": 859608,
      "minutes": 45,
      "score": 2,
      "type": "pass"
    },
    {
      "additional_minutes": 0,
      "corrected": false,
      "datetime": "2020-09-26T14:12:34Z",
      "id": 859337,
      "minutes": 42,
      "score": 2,
      "type": "pass"
    },
    {
      "additional_minutes": 0,
      "corrected": false,
      "datetime": "2020-09-26T14:37:01Z",
      "id": 860079,
      "minutes": 47,
      "score": -10,
      "type": "unsuccessfulTackle"
    },
    {
      "additional_minutes": 0,
      "corrected": false,
      "datetime": "2020-09-26T14:37:01Z",
      "id": 860093,
      "minutes": 48,
      "score": 2,
      "type": "pass"
    },
    {
      "additional_minutes": 0,
      "corrected": false,
      "datetime": "2020-09-26T14:40:31Z",
      "id": 860389,
      "minutes": 52,
      "score": 2,
      "type": "pass"
    },
    {
      "additional_minutes": 0,
      "corrected": false,
      "datetime": "2020-09-26T14:34:01Z",
      "id": 859965,
      "minutes": 46,
      "score": 2,
      "type": "pass"
    },
    {
      "additional_minutes": 0,
      "corrected": false,
      "datetime": "2020-09-26T14:37:01Z",
      "id": 860088,
      "minutes": 48,
      "score": 2,
      "type": "pass"
    },
    {
      "additional_minutes": 0,
      "corrected": false,
      "datetime": "2020-09-26T14:35:02Z",
      "id": 860018,
      "minutes": 46,
      "score": 2,
      "type": "pass"
    },
    {
      "additional_minutes": 0,
      "corrected": false,
      "datetime": "2020-09-26T14:35:03Z",
      "id": 860038,
      "minutes": 47,
      "score": 18,
      "type": "cross"
    },
    {
      "additional_minutes": 0,
      "corrected": false,
      "datetime": "2020-09-26T14:37:01Z",
      "id": 860095,
      "minutes": 48,
      "score": -2,
      "type": "unsuccessfulPass"
    },
    {
      "additional_minutes": 0,
      "corrected": false,
      "datetime": "2020-09-26T14:37:01Z",
      "id": 860098,
      "minutes": 49,
      "score": -15,
      "type": "foul"
    },
    {
      "additional_minutes": 0,
      "corrected": false,
      "datetime": "2020-09-26T14:35:02Z",
      "id": 860016,
      "minutes": 46,
      "score": 2,
      "type": "pass"
    },
    {
      "additional_minutes": 0,
      "corrected": false,
      "datetime": "2020-09-26T14:35:02Z",
      "id": 860027,
      "minutes": 46,
      "score": 2,
      "type": "pass"
    },
    {
      "additional_minutes": 0,
      "corrected": false,
      "datetime": "2020-09-26T14:39:31Z",
      "id": 860335,
      "minutes": 51,
      "score": 2,
      "type": "pass"
    },
    {
      "additional_minutes": 0,
      "corrected": false,
      "datetime": "2020-09-26T14:38:31Z",
      "id": 860254,
      "minutes": 49,
      "score": 15,
      "type": "successfulTackle"
    },
    {
      "additional_minutes": 0,
      "corrected": false,
      "datetime": "2020-09-26T14:44:01Z",
      "id": 860621,
      "minutes": 55,
      "score": 2,
      "type": "pass"
    },
    {
      "additional_minutes": 0,
      "corrected": false,
      "datetime": "2020-09-26T14:38:31Z",
      "id": 860269,
      "minutes": 50,
      "score": 18,
      "type": "cross"
    },
    {
      "additional_minutes": 0,
      "corrected": false,
      "datetime": "2020-09-26T14:38:31Z",
      "id": 860258,
      "minutes": 49,
      "score": 2,
      "type": "pass"
    },
    {
      "additional_minutes": 0,
      "corrected": false,
      "datetime": "2020-09-26T14:39:31Z",
      "id": 860334,
      "minutes": 51,
      "score": 15,
      "type": "interception"
    },
    {
      "additional_minutes": 0,
      "corrected": false,
      "datetime": "2020-09-26T14:48:01Z",
      "id": 860941,
      "minutes": 59,
      "score": 2,
      "type": "pass"
    },
    {
      "additional_minutes": 0,
      "corrected": false,
      "datetime": "2020-09-26T14:46:31Z",
      "id": 860845,
      "minutes": 56,
      "score": -2,
      "type": "unsuccessfulPass"
    },
    {
      "additional_minutes": 0,
      "corrected": false,
      "datetime": "2020-09-26T14:50:32Z",
      "id": 861154,
      "minutes": 62,
      "score": 2,
      "type": "pass"
    },
    {
      "additional_minutes": 0,
      "corrected": false,
      "datetime": "2020-09-26T14:53:01Z",
      "id": 861342,
      "minutes": 64,
      "score": -2,
      "type": "unsuccessfulPass"
    },
    {
      "additional_minutes": 0,
      "corrected": false,
      "datetime": "2020-09-26T14:49:01Z",
      "id": 861008,
      "minutes": 60,
      "score": 2,
      "type": "pass"
    },
    {
      "additional_minutes": 0,
      "corrected": false,
      "datetime": "2020-09-26T14:46:31Z",
      "id": 860861,
      "minutes": 57,
      "score": 2,
      "type": "pass"
    },
    {
      "additional_minutes": 0,
      "corrected": false,
      "datetime": "2020-09-26T14:49:01Z",
      "id": 861019,
      "minutes": 61,
      "score": 2,
      "type": "pass"
    },
    {
      "additional_minutes": 0,
      "corrected": false,
      "datetime": "2020-09-26T14:46:31Z",
      "id": 860857,
      "minutes": 57,
      "score": 2,
      "type": "pass"
    },
    {
      "additional_minutes": 0,
      "corrected": false,
      "datetime": "2020-09-26T14:50:32Z",
      "id": 861152,
      "minutes": 61,
      "score": 2,
      "type": "pass"
    },
    {
      "additional_minutes": 0,
      "corrected": false,
      "datetime": "2020-09-26T14:50:32Z",
      "id": 861156,
      "minutes": 62,
      "score": 2,
      "type": "pass"
    },
    {
      "additional_minutes": 0,
      "corrected": false,
      "datetime": "2020-09-26T14:48:01Z",
      "id": 860943,
      "minutes": 59,
      "score": 2,
      "type": "pass"
    },
    {
      "additional_minutes": 0,
      "corrected": false,
      "datetime": "2020-09-26T14:50:32Z",
      "id": 861158,
      "minutes": 62,
      "score": 18,
      "type": "cross"
    },
    {
      "additional_minutes": 0,
      "corrected": false,
      "datetime": "2020-09-26T14:50:31Z",
      "id": 861142,
      "minutes": 61,
      "score": 2,
      "type": "pass"
    },
    {
      "additional_minutes": 0,
      "corrected": false,
      "datetime": "2020-09-26T14:58:31Z",
      "id": 861694,
      "minutes": 69,
      "score": 2,
      "type": "pass"
    },
    {
      "additional_minutes": 0,
      "corrected": false,
      "datetime": "2020-09-26T14:58:32Z",
      "id": 861704,
      "minutes": 70,
      "score": 2,
      "type": "pass"
    },
    {
      "additional_minutes": 0,
      "corrected": false,
      "datetime": "2020-09-26T14:58:32Z",
      "id": 861706,
      "minutes": 70,
      "score": 2,
      "type": "pass"
    },
    {
      "additional_minutes": 0,
      "corrected": false,
      "datetime": "2020-09-26T14:52:01Z",
      "id": 861255,
      "minutes": 63,
      "score": 2,
      "type": "pass"
    },
    {
      "additional_minutes": 0,
      "corrected": false,
      "datetime": "2020-09-26T14:52:01Z",
      "id": 861260,
      "minutes": 63,
      "score": 2,
      "type": "pass"
    },
    {
      "additional_minutes": 0,
      "corrected": false,
      "datetime": "2020-09-26T14:52:01Z",
      "id": 861262,
      "minutes": 63,
      "score": 2,
      "type": "pass"
    },
    {
      "additional_minutes": 0,
      "corrected": false,
      "datetime": "2020-09-26T14:52:02Z",
      "id": 861273,
      "minutes": 63,
      "score": 2,
      "type": "pass"
    },
    {
      "additional_minutes": 0,
      "corrected": false,
      "datetime": "2020-09-26T14:53:01Z",
      "id": 861345,
      "minutes": 64,
      "score": 2,
      "type": "pass"
    },
    {
      "additional_minutes": 0,
      "corrected": false,
      "datetime": "2020-09-26T15:00:01Z",
      "id": 861805,
      "minutes": 70,
      "score": 2,
      "type": "pass"
    },
    {
      "additional_minutes": 0,
      "corrected": false,
      "datetime": "2020-09-26T15:00:31Z",
      "id": 861883,
      "minutes": 71,
      "score": 2,
      "type": "pass"
    },
    {
      "additional_minutes": 0,
      "corrected": false,
      "datetime": "2020-09-26T14:56:31Z",
      "id": 861557,
      "minutes": 68,
      "score": 2,
      "type": "pass"
    },
    {
      "additional_minutes": 0,
      "corrected": false,
      "datetime": "2020-09-26T15:00:31Z",
      "id": 861885,
      "minutes": 72,
      "score": 2,
      "type": "pass"
    },
    {
      "additional_minutes": 0,
      "corrected": false,
      "datetime": "2020-09-26T15:00:31Z",
      "id": 861889,
      "minutes": 72,
      "score": 2,
      "type": "pass"
    },
    {
      "additional_minutes": 0,
      "corrected": false,
      "datetime": "2020-09-26T14:58:31Z",
      "id": 861691,
      "minutes": 68,
      "score": 2,
      "type": "pass"
    },
    {
      "additional_minutes": 0,
      "corrected": false,
      "datetime": "2020-09-26T15:00:31Z",
      "id": 861881,
      "minutes": 71,
      "score": 2,
      "type": "pass"
    },
    {
      "additional_minutes": 0,
      "corrected": false,
      "datetime": "2020-09-26T15:03:02Z",
      "id": 861989,
      "minutes": 73,
      "score": 2,
      "type": "pass"
    },
    {
      "additional_minutes": 0,
      "corrected": false,
      "datetime": "2020-09-26T15:03:02Z",
      "id": 861994,
      "minutes": 73,
      "score": 2,
      "type": "pass"
    },
    {
      "additional_minutes": 0,
      "corrected": false,
      "datetime": "2020-09-26T15:00:01Z",
      "id": 861810,
      "minutes": 70,
      "score": 2,
      "type": "pass"
    },
    {
      "additional_minutes": 0,
      "corrected": false,
      "datetime": "2020-09-26T15:03:02Z",
      "id": 862004,
      "minutes": 73,
      "score": 2,
      "type": "pass"
    },
    {
      "additional_minutes": 0,
      "corrected": false,
      "datetime": "2020-09-26T15:03:03Z",
      "id": 862024,
      "minutes": 75,
      "score": 2,
      "type": "pass"
    },
    {
      "additional_minutes": 0,
      "corrected": false,
      "datetime": "2020-09-26T15:06:32Z",
      "id": 862276,
      "minutes": 78,
      "score": -10,
      "type": "unsuccessfulTackle"
    },
    {
      "additional_minutes": 0,
      "corrected": false,
      "datetime": "2020-09-26T15:07:32Z",
      "id": 862346,
      "minutes": 78,
      "score": 2,
      "type": "pass"
    },
    {
      "additional_minutes": 0,
      "corrected": false,
      "datetime": "2020-09-26T15:03:02Z",
      "id": 861999,
      "minutes": 73,
      "score": 2,
      "type": "pass"
    },
    {
      "additional_minutes": 0,
      "corrected": false,
      "datetime": "2020-09-26T15:06:31Z",
      "id": 862253,
      "minutes": 77,
      "score": 2,
      "type": "pass"
    },
    {
      "additional_minutes": 1,
      "corrected": false,
      "datetime": "2020-09-26T15:19:32Z",
      "id": 863214,
      "minutes": 90,
      "score": 2,
      "type": "pass"
    },
    {
      "additional_minutes": 0,
      "corrected": false,
      "datetime": "2020-09-26T15:03:03Z",
      "id": 862029,
      "minutes": 75,
      "score": 2,
      "type": "pass"
    },
    {
      "additional_minutes": 0,
      "corrected": false,
      "datetime": "2020-09-26T15:04:31Z",
      "id": 862101,
      "minutes": 76,
      "score": -30,
      "type": "yellowCard"
    },
    {
      "additional_minutes": 0,
      "corrected": false,
      "datetime": "2020-09-26T15:09:32Z",
      "id": 862485,
      "minutes": 80,
      "score": -2,
      "type": "unsuccessfulPass"
    },
    {
      "additional_minutes": 0,
      "corrected": false,
      "datetime": "2020-09-26T15:12:01Z",
      "id": 862621,
      "minutes": 83,
      "score": 2,
      "type": "pass"
    },
    {
      "additional_minutes": 0,
      "corrected": false,
      "datetime": "2020-09-26T15:06:31Z",
      "id": 862262,
      "minutes": 77,
      "score": 2,
      "type": "pass"
    },
    {
      "additional_minutes": 0,
      "corrected": false,
      "datetime": "2020-09-26T15:09:31Z",
      "id": 862469,
      "minutes": 79,
      "score": -10,
      "type": "unsuccessfulTackle"
    },
    {
      "additional_minutes": 0,
      "corrected": false,
      "datetime": "2020-09-26T15:12:01Z",
      "id": 862623,
      "minutes": 83,
      "score": 2,
      "type": "pass"
    },
    {
      "additional_minutes": 0,
      "corrected": false,
      "datetime": "2020-09-26T15:14:32Z",
      "id": 862898,
      "minutes": 86,
      "score": 2,
      "type": "pass"
    },
    {
      "additional_minutes": 0,
      "corrected": false,
      "datetime": "2020-09-26T15:09:32Z",
      "id": 862482,
      "minutes": 80,
      "score": 2,
      "type": "pass"
    },
    {
      "additional_minutes": 0,
      "corrected": false,
      "datetime": "2020-09-26T15:12:02Z",
      "id": 862632,
      "minutes": 83,
      "score": 12,
      "type": "superPass"
    },
    {
      "additional_minutes": 0,
      "corrected": false,
      "datetime": "2020-09-26T15:13:01Z",
      "id": 862782,
      "minutes": 84,
      "score": 2,
      "type": "pass"
    },
    {
      "additional_minutes": 0,
      "corrected": false,
      "datetime": "2020-09-26T15:16:32Z",
      "id": 862961,
      "minutes": 87,
      "score": -2,
      "type": "unsuccessfulPass"
    },
    {
      "additional_minutes": 0,
      "corrected": false,
      "datetime": "2020-09-26T15:13:01Z",
      "id": 862780,
      "minutes": 84,
      "score": 2,
      "type": "pass"
    },
    {
      "additional_minutes": 0,
      "corrected": false,
      "datetime": "2020-09-26T15:17:01Z",
      "id": 863074,
      "minutes": 88,
      "score": 12,
      "type": "superPass"
    },
    {
      "additional_minutes": 0,
      "corrected": false,
      "datetime": "2020-09-26T15:19:32Z",
      "id": 863203,
      "minutes": 90,
      "score": 2,
      "type": "pass"
    },
    {
      "additional_minutes": 0,
      "corrected": false,
      "datetime": "2020-09-26T15:19:32Z",
      "id": 863205,
      "minutes": 90,
      "score": 2,
      "type": "pass"
    },
    {
      "additional_minutes": 0,
      "corrected": false,
      "datetime": "2020-09-26T15:19:31Z",
      "id": 863200,
      "minutes": 90,
      "score": -10,
      "type": "unsuccessfulTackle"
    },
    {
      "additional_minutes": 0,
      "corrected": false,
      "datetime": "2020-09-26T15:19:32Z",
      "id": 863202,
      "minutes": 90,
      "score": 15,
      "type": "successfulTackle"
    },
    {
      "additional_minutes": 1,
      "corrected": false,
      "datetime": "2020-09-26T15:21:31Z",
      "id": 863308,
      "minutes": 90,
      "score": 2,
      "type": "pass"
    },
    {
      "additional_minutes": 4,
      "corrected": false,
      "datetime": "2020-09-26T15:23:01Z",
      "id": 863400,
      "minutes": 90,
      "score": 2,
      "type": "pass"
    }
  ]
}