{
  "aggregated_events": [
    {
      "occurrences": 1,
      "score": 100,
      "type": "goalAssist"
    },
    {
      "occurrences": 2,
      "score": -40,
      "type": "goalMissedFar"
    },
    {
      "occurrences": 2,
      "score": -30,
      "type": "offside"
    },
    {
      "occurrences": 21,
      "score": 42,
      "type": "pass"
    },
    {
      "occurrences": 5,
      "score": 250,
      "type": "shotAtGoal"
    },
    {
      "occurrences": 5,
      "score": 75,
      "type": "successfulTackle"
    },
    {
      "occurrences": 1,
      "score": 2,
      "type": "throwIn"
    },
    {
      "occurrences": 12,
      "score": -24,
      "type": "unsuccessfulPass"
    },
    {
      "occurrences": 4,
      "score": -40,
      "type": "unsuccessfulTackle"
    }
  ],
  "events": [
    {
      "additional_minutes": 0,
      "corrected": false,
      "datetime": "2020-10-03T13:35:03Z",
      "id": 869536,
      "minutes": 4,
      "score": 50,
      "type": "shotAtGoal"
    },
    {
      "additional_minutes": 0,
      "corrected": false,
      "datetime": "2020-10-03T13:44:01Z",
      "id": 870128,
      "minutes": 12,
      "score": -20,
      "type": "goalMissedFar"
    },
    {
      "additional_minutes": 0,
      "corrected": false,
      "datetime": "2020-10-03T13:35:03Z",
      "id": 869529,
      "minutes": 4,
      "score": 2,
      "type": "pass"
    },
    {
      "additional_minutes": 0,
      "corrected": false,
      "datetime": "2020-10-03T13:35:03Z",
      "id": 869532,
      "minutes": 4,
      "score": 2,
      "type": "pass"
    },
    {
      "additional_minutes": 0,
      "corrected": false,
      "datetime": "2020-10-03T13:35:03Z",
      "id": 869527,
      "minutes": 4,
      "score": -2,
      "type": "unsuccessfulPass"
    },
    {
      "additional_minutes": 0,
      "corrected": false,
      "datetime": "2020-10-03T13:40:04Z",
      "id": 869904,
      "minutes": 8,
      "score": -10,
      "type": "unsuccessfulTackle"
    },
    {
      "additional_minutes": 0,
      "corrected": false,
      "datetime": "2020-10-03T13:44:01Z",
      "id": 870124,
      "minutes": 12,
      "score": -2,
      "type": "unsuccessfulPass"
    },
    {
      "additional_minutes": 0,
      "corrected": false,
      "datetime": "2020-10-03T13:44:01Z",
      "id": 870125,
      "minutes": 12,
      "score": 2,
      "type": "pass"
    },
    {
      "additional_minutes": 0,
      "corrected": false,
      "datetime": "2020-10-03T13:45:16Z",
      "id": 870249,
      "minutes": 14,
      "score": -2,
      "type": "unsuccessfulPass"
    },
    {
      "additional_minutes": 0,
      "corrected": false,
      "datetime": "2020-10-03T13:40:04Z",
      "id": 869903,
      "minutes": 8,
      "score": -2,
      "type": "unsuccessfulPass"
    },
    {
      "additional_minutes": 0,
      "corrected": false,
      "datetime": "2020-10-03T13:40:04Z",
      "id": 869912,
      "minutes": 8,
      "score": -2,
      "type": "unsuccessfulPass"
    },
    {
      "additional_minutes": 0,
      "corrected": false,
      "datetime": "2020-10-03T13:55:02Z",
      "id": 870930,
      "minutes": 20,
      "score": -2,
      "type": "unsuccessfulPass"
    },
    {
      "additional_minutes": 0,
      "corrected": false,
      "datetime": "2020-10-03T13:55:02Z",
      "id": 870928,
      "minutes": 20,
      "score": 2,
      "type": "pass"
    },
    {
      "additional_minutes": 0,
      "corrected": false,
      "datetime": "2020-10-03T13:55:03Z",
      "id": 870935,
      "minutes": 20,
      "score": 2,
      "type": "pass"
    },
    {
      "additional_minutes": 0,
      "corrected": false,
      "datetime": "2020-10-03T14:03:01Z",
      "id": 871623,
      "minutes": 31,
      "score": 2,
      "type": "pass"
    },
    {
      "additional_minutes": 0,
      "corrected": false,
      "datetime": "2020-10-03T14:03:01Z",
      "id": 871621,
      "minutes": 31,
      "score": 15,
      "type": "successfulTackle"
    },
    {
      "additional_minutes": 0,
      "corrected": false,
      "datetime": "2020-10-03T14:00:02Z",
      "id": 871445,
      "minutes": 29,
      "score": -10,
      "type": "unsuccessfulTackle"
    },
    {
      "additional_minutes": 0,
      "corrected": false,
      "datetime": "2020-10-03T14:03:32Z",
      "id": 871653,
      "minutes": 32,
      "score": -15,
      "type": "offside"
    },
    {
      "additional_minutes": 0,
      "corrected": false,
      "datetime": "2020-10-03T14:11:02Z",
      "id": 872245,
      "minutes": 39,
      "score": 2,
      "type": "pass"
    },
    {
      "additional_minutes": 0,
      "corrected": false,
      "datetime": "2020-10-03T14:14:02Z",
      "id": 872455,
      "minutes": 42,
      "score": 2,
      "type": "pass"
    },
    {
      "additional_minutes": 0,
      "corrected": false,
      "datetime": "2020-10-03T14:14:03Z",
      "id": 872459,
      "minutes": 43,
      "score": 2,
      "type": "pass"
    },
    {
      "additional_minutes": 1,
      "corrected": false,
      "datetime": "2020-10-03T14:18:02Z",
      "id": 872764,
      "minutes": 45,
      "score": 15,
      "type": "successfulTackle"
    },
    {
      "additional_minutes": 1,
      "corrected": false,
      "datetime": "2020-10-03T14:18:02Z",
      "id": 872766,
      "minutes": 45,
      "score": 2,
      "type": "pass"
    },
    {
      "additional_minutes": 0,
      "corrected": false,
      "datetime": "2020-10-03T14:34:32Z",
      "id": 872975,
      "minutes": 46,
      "score": 2,
      "type": "pass"
    },
    {
      "additional_minutes": 0,
      "corrected": false,
      "datetime": "2020-10-03T14:36:02Z",
      "id": 873029,
      "minutes": 46,
      "score": 2,
      "type": "pass"
    },
    {
      "additional_minutes": 0,
      "corrected": false,
      "datetime": "2020-10-03T14:38:02Z",
      "id": 873197,
      "minutes": 47,
      "score": 50,
      "type": "shotAtGoal"
    },
    {
      "additional_minutes": 0,
      "corrected": false,
      "datetime": "2020-10-03T14:42:33Z",
      "id": 873554,
      "minutes": 53,
      "score": 2,
      "type": "pass"
    },
    {
      "additional_minutes": 0,
      "corrected": false,
      "datetime": "2020-10-03T14:39:04Z",
      "id": 873282,
      "minutes": 49,
      "score": 2,
      "type": "pass"
    },
    {
      "additional_minutes": 0,
      "corrected": false,
      "datetime": "2020-10-03T14:42:33Z",
      "id": 873557,
      "minutes": 53,
      "score": 2,
      "type": "throwIn"
    },
    {
      "additional_minutes": 0,
      "corrected": false,
      "datetime": "2020-10-03T14:47:31Z",
      "id": 873832,
      "minutes": 57,
      "score": -2,
      "type": "unsuccessfulPass"
    },
    {
      "additional_minutes": 0,
      "corrected": false,
      "datetime": "2020-10-03T14:49:04Z",
      "id": 873945,
      "minutes": 59,
      "score": 50,
      "type": "shotAtGoal"
    },
    {
      "additional_minutes": 0,
      "corrected": false,
      "datetime": "2020-10-03T14:46:02Z",
      "id": 873772,
      "minutes": 56,
      "score": 2,
      "type": "pass"
    },
    {
      "additional_minutes": 0,
      "corrected": false,
      "datetime": "2020-10-03T14:42:33Z",
      "id": 873559,
      "minutes": 53,
      "score": -2,
      "type": "unsuccessfulPass"
    },
    {
      "additional_minutes": 0,
      "corrected": false,
      "datetime": "2020-10-03T14:44:32Z",
      "id": 873705,
      "minutes": 53,
      "score": 2,
      "type": "pass"
    },
    {
      "additional_minutes": 0,
      "corrected": false,
      "datetime": "2020-10-03T14:44:32Z",
      "id": 873709,
      "minutes": 54,
      "score": -2,
      "type": "unsuccessfulPass"
    },
    {
      "additional_minutes": 0,
      "corrected": false,
      "datetime": "2020-10-03T14:47:31Z",
      "id": 873830,
      "minutes": 57,
      "score": 2,
      "type": "pass"
    },
    {
      "additional_minutes": 0,
      "corrected": false,
      "datetime": "2020-10-03T14:51:33Z",
      "id": 874163,
      "minutes": 60,
      "score": 2,
      "type": "pass"
    },
    {
      "additional_minutes": 0,
      "corrected": false,
      "datetime": "2020-10-03T14:51:33Z",
      "id": 874161,
      "minutes": 60,
      "score": 15,
      "type": "successfulTackle"
    },
    {
      "additional_minutes": 0,
      "corrected": false,
      "datetime": "2020-10-03T14:49:04Z",
      "id": 873940,
      "minutes": 59,
      "score": 2,
      "type": "pass"
    },
    {
      "additional_minutes": 0,
      "corrected": false,
      "datetime": "2020-10-03T14:53:02Z",
      "id": 874291,
      "minutes": 63,
      "score": -2,
      "type": "unsuccessfulPass"
    },
    {
      "additional_minutes": 0,
      "corrected": false,
      "datetime": "2020-10-03T14:54:33Z",
      "id": 874439,
      "minutes": 66,
      "score": 2,
      "type": "pass"
    },
    {
      "additional_minutes": 0,
      "corrected": false,
      "datetime": "2020-10-03T14:56:41Z",
      "id": 874526,
      "minutes": 66,
      "score": -20,
      "type": "goalMissedFar"
    },
    {
      "additional_minutes": 0,
      "corrected": false,
      "datetime": "2020-10-03T15:05:03Z",
      "id": 875052,
      "minutes": 68,
      "score": 50,
      "type": "shotAtGoal"
    },
    {
      "additional_minutes": 0,
      "corrected": false,
      "datetime": "2020-10-03T15:05:07Z",
      "id": 875078,
      "minutes": 74,
      "score": 15,
      "type": "successfulTackle"
    },
    {
      "additional_minutes": 0,
      "corrected": false,
      "datetime": "2020-10-03T15:05:08Z",
      "id": 875092,
      "minutes": 75,
      "score": 15,
      "type": "successfulTackle"
    },
    {
      "additional_minutes": 0,
      "corrected": false,
      "datetime": "2020-10-03T15:05:03Z",
      "id": 875056,
      "minutes": 71,
      "score": 100,
      "type": "goalAssist"
    },
    {
      "additional_minutes": 0,
      "corrected": false,
      "datetime": "2020-10-03T15:05:03Z",
      "id": 875055,
      "minutes": 71,
      "score": 50,
      "type": "shotAtGoal"
    },
    {
      "additional_minutes": 0,
      "corrected": false,
      "datetime": "2020-10-03T15:05:08Z",
      "id": 875094,
      "minutes": 75,
      "score": -2,
      "type": "unsuccessfulPass"
    },
    {
      "additional_minutes": 0,
      "corrected": false,
      "datetime": "2020-10-03T15:11:05Z",
      "id": 875544,
      "minutes": 81,
      "score": -15,
      "type": "offside"
    },
    {
      "additional_minutes": 0,
      "corrected": false,
      "datetime": "2020-10-03T15:07:06Z",
      "id": 875235,
      "minutes": 77,
      "score": 2,
      "type": "pass"
    },
    {
      "additional_minutes": 0,
      "corrected": false,
      "datetime": "2020-10-03T15:12:05Z",
      "id": 875669,
      "minutes": 83,
      "score": -10,
      "type": "unsuccessfulTackle"
    },
    {
      "additional_minutes": 0,
      "corrected": false,
      "datetime": "2020-10-03T15:17:33Z",
      "id": 876004,
      "minutes": 88,
      "score": -2,
      "type": "unsuccessfulPass"
    },
    {
      "additional_minutes": 0,
      "corrected": false,
      "datetime": "2020-10-03T15:15:03Z",
      "id": 875916,
      "minutes": 85,
      "score": -10,
      "type": "unsuccessfulTackle"
    }
  ]
}